easy_logstash/__init__.py
easy_logstash/constants.py
easy_logstash/django_logstash_config.py
easy_logstash/handler.py
easy_logstash/logstash_config.py
easy_logstash-1.0.0.dist-info/LICENSE
easy_logstash-1.0.0.dist-info/METADATA
easy_logstash-1.0.0.dist-info/WHEEL
easy_logstash-1.0.0.dist-info/top_level.txt
easy_logstash-1.0.0.dist-info/RECORD
