Metadata-Version: 2.1
Name: easy-logstash
Version: 1.0.0
Summary: A easy way to handle logs with logstash.
Home-page: https://github.com/ptbang/Easy-Logstash
Author: Bang Phan (ptbang)
Author-email: ptbang@gmail.com
Maintainer: Bang Phan
License: MIT
Project-URL: Documentation, https://github.com/ptbang/Easy-Logstash
Keywords: logstash logging async easy simple
Classifier: Development Status :: 4 - Beta
Classifier: Intended Audience :: Developers
Classifier: License :: OSI Approved :: MIT License
Classifier: Operating System :: OS Independent
Classifier: Programming Language :: Python
Classifier: Programming Language :: Python :: 3.10
Classifier: Programming Language :: Python :: 3.11
License-File: LICENSE
Requires-Dist: python-logstash-async >=2.5
